{"y":"gp","dates":["04\/26\/2023"],"series":[{"name":"Ro'bi wan","id":"124599552","values":{"Shaak Ti":[-1],"JKR":[163474],"CLS-Alt":[-1],"ROLO":[134023],"KAM Squad":[152543],"Mon Mothma":[96830],"Negotiator":[485190],"JMLS":[180856],"Padme":[-1],"GL Rey":[-1],"GAS":[-1],"Clones":[-1],"JKL":[147576],"CLS":[-1],"JTR":[-1],"GR Jedi":[-1],"JMK GR":[179902],"JMK Jedi":[-1],"GAS Special":[69290],"Finn":[149630]}},{"name":"Mandalorion Jrnyman","id":"126964277","values":{"Shaak Ti":[135998],"JKR":[126182],"ROLO":[125132],"CLS-Alt":[-1],"KAM Squad":[135998],"Mon Mothma":[61635],"Negotiator":[403549],"JMLS":[-1],"Padme":[139114],"GL Rey":[-1],"GAS":[-1],"Clones":[-1],"JKL":[-1],"CLS":[-1],"JTR":[-1],"GR Jedi":[-1],"JMK GR":[-1],"JMK Jedi":[-1],"GAS Special":[-1],"Finn":[-1]}},{"name":"Vaders Fist","id":"128286681","values":{"Shaak Ti":[-1],"JKR":[145339],"ROLO":[123917],"CLS-Alt":[-1],"KAM Squad":[145789],"Mon Mothma":[91888],"Negotiator":[465191],"JMLS":[174335],"Padme":[-1],"GL Rey":[165128],"GAS":[-1],"Clones":[-1],"JKL":[142875],"CLS":[-1],"JTR":[151493],"GR Jedi":[-1],"JMK GR":[187375],"JMK Jedi":[172134],"GAS Special":[65916],"Finn":[-1]}},{"name":"Wasburn09","id":"129783432","values":{"Shaak Ti":[136547],"JKR":[148992],"ROLO":[117499],"CLS-Alt":[-1],"KAM Squad":[136547],"Mon Mothma":[-1],"Negotiator":[418021],"JMLS":[-1],"Padme":[135539],"GL Rey":[-1],"GAS":[-1],"Clones":[-1],"JKL":[150501],"CLS":[-1],"JTR":[-1],"GR Jedi":[-1],"JMK GR":[-1],"JMK Jedi":[-1],"GAS Special":[63031],"Finn":[-1]}},{"name":"Lars Quell","id":"151487741","values":{"Shaak Ti":[137910],"JKR":[122355],"ROLO":[112399],"CLS-Alt":[-1],"KAM Squad":[137910],"Mon Mothma":[-1],"Negotiator":[444714],"JMLS":[-1],"Padme":[131098],"GL Rey":[-1],"GAS":[-1],"Clones":[-1],"JKL":[-1],"CLS":[123121],"JTR":[-1],"GR Jedi":[-1],"JMK GR":[171449],"JMK Jedi":[159029],"GAS Special":[58038],"Finn":[-1]}},{"name":"Jcerillo70","id":"177357652","values":{"Shaak Ti":[-1],"JKR":[131440],"ROLO":[-1],"CLS-Alt":[-1],"KAM Squad":[151023],"Mon Mothma":[69039],"Negotiator":[460242],"JMLS":[-1],"Padme":[-1],"GL Rey":[-1],"GAS":[-1],"Clones":[-1],"JKL":[127811],"CLS":[137256],"JTR":[-1],"GR Jedi":[-1],"JMK GR":[180636],"JMK Jedi":[-1],"GAS Special":[65677],"Finn":[64818]}},{"name":"Walan Lamor","id":"181994418","values":{"Shaak Ti":[108121],"JKR":[139038],"ROLO":[92278],"CLS-Alt":[128402],"KAM Squad":[108121],"Mon Mothma":[-1],"Negotiator":[387838],"JMLS":[-1],"Padme":[-1],"GL Rey":[142844],"GAS":[-1],"Clones":[-1],"JKL":[-1],"CLS":[-1],"JTR":[-1],"GR Jedi":[-1],"JMK GR":[-1],"JMK Jedi":[-1],"GAS Special":[49615],"Finn":[-1]}},{"name":"Wrongfulpuppet","id":"232337688","values":{"Shaak Ti":[134663],"JKR":[137975],"ROLO":[-1],"CLS-Alt":[-1],"KAM Squad":[134663],"Mon Mothma":[-1],"Negotiator":[411933],"JMLS":[-1],"Padme":[116191],"GL Rey":[-1],"GAS":[-1],"Clones":[-1],"JKL":[150882],"CLS":[145483],"JTR":[-1],"GR Jedi":[-1],"JMK GR":[-1],"JMK Jedi":[-1],"GAS Special":[65616],"Finn":[-1]}},{"name":"Griffin","id":"236743442","values":{"Shaak Ti":[143019],"JKR":[145314],"ROLO":[123512],"CLS-Alt":[-1],"KAM Squad":[143019],"Mon Mothma":[107310],"Negotiator":[450022],"JMLS":[173817],"Padme":[-1],"GL Rey":[163835],"GAS":[-1],"Clones":[-1],"JKL":[146235],"CLS":[-1],"JTR":[-1],"GR Jedi":[-1],"JMK GR":[185312],"JMK Jedi":[-1],"GAS Special":[66323],"Finn":[-1]}},{"name":"darthAnology","id":"268848548","values":{"Shaak Ti":[-1],"JKR":[149528],"ROLO":[-1],"CLS-Alt":[-1],"KAM Squad":[155377],"Mon Mothma":[107869],"Negotiator":[477440],"JMLS":[178280],"Padme":[-1],"GL Rey":[-1],"GAS":[-1],"Clones":[-1],"JKL":[145125],"CLS":[145550],"JTR":[-1],"GR Jedi":[-1],"JMK GR":[182902],"JMK Jedi":[-1],"GAS Special":[65896],"Finn":[149101]}},{"name":"JasSolo","id":"273222174","values":{"Shaak Ti":[-1],"JKR":[139777],"ROLO":[123816],"CLS-Alt":[-1],"KAM Squad":[119169],"Mon Mothma":[94097],"Negotiator":[429035],"JMLS":[165619],"Padme":[-1],"GL Rey":[166352],"GAS":[124362],"Clones":[112003],"JKL":[185568],"CLS":[-1],"JTR":[-1],"GR Jedi":[-1],"JMK GR":[174855],"JMK Jedi":[-1],"GAS Special":[63408],"Finn":[-1]}},{"name":"BazookaJoe","id":"282763552","values":{"Shaak Ti":[-1],"JKR":[156985],"ROLO":[124176],"CLS-Alt":[-1],"KAM Squad":[142452],"Mon Mothma":[90185],"Negotiator":[490641],"JMLS":[181722],"Padme":[-1],"GL Rey":[-1],"GAS":[-1],"Clones":[-1],"JKL":[142986],"CLS":[-1],"JTR":[117413],"GR Jedi":[-1],"JMK GR":[181357],"JMK Jedi":[-1],"GAS Special":[69607],"Finn":[-1]}},{"name":"Gman3D 2","id":"369548148","values":{"Shaak Ti":[-1],"JKR":[133963],"ROLO":[-1],"CLS-Alt":[-1],"KAM Squad":[138564],"Mon Mothma":[92984],"Negotiator":[457111],"JMLS":[159902],"Padme":[-1],"GL Rey":[-1],"GAS":[-1],"Clones":[-1],"JKL":[163432],"CLS":[140864],"JTR":[-1],"GR Jedi":[-1],"JMK GR":[169836],"JMK Jedi":[-1],"GAS Special":[63244],"Finn":[-1]}},{"name":"Holmahnootz","id":"375133234","values":{"Shaak Ti":[-1],"JKR":[140453],"ROLO":[100018],"CLS-Alt":[-1],"KAM Squad":[131856],"Mon Mothma":[-1],"Negotiator":[454534],"JMLS":[174218],"Padme":[-1],"GL Rey":[-1],"GAS":[-1],"Clones":[-1],"JKL":[144300],"CLS":[140264],"JTR":[-1],"GR Jedi":[151080],"JMK GR":[172423],"JMK Jedi":[-1],"GAS Special":[63832],"Finn":[-1]}},{"name":"ThanosLeftHand","id":"386556243","values":{"Shaak Ti":[-1],"JKR":[147791],"ROLO":[118111],"CLS-Alt":[-1],"KAM Squad":[152851],"Mon Mothma":[96974],"Negotiator":[478237],"JMLS":[173391],"Padme":[-1],"GL Rey":[162478],"GAS":[-1],"Clones":[-1],"JKL":[141402],"CLS":[-1],"JTR":[152948],"GR Jedi":[-1],"JMK GR":[182221],"JMK Jedi":[-1],"GAS Special":[67549],"Finn":[-1]}},{"name":"Wolfenstien","id":"431257189","values":{"Shaak Ti":[-1],"JKR":[128219],"ROLO":[131850],"CLS-Alt":[-1],"KAM Squad":[143445],"Mon Mothma":[66520],"Negotiator":[461064],"JMLS":[-1],"Padme":[-1],"GL Rey":[-1],"GAS":[-1],"Clones":[-1],"JKL":[133465],"CLS":[-1],"JTR":[-1],"GR Jedi":[-1],"JMK GR":[174378],"JMK Jedi":[-1],"GAS Special":[60060],"Finn":[62376]}},{"name":"KailonTheGrey","id":"445222445","values":{"Shaak Ti":[-1],"JKR":[153027],"ROLO":[126070],"CLS-Alt":[-1],"KAM Squad":[151228],"Mon Mothma":[99728],"Negotiator":[468564],"JMLS":[175110],"Padme":[-1],"GL Rey":[162176],"GAS":[-1],"Clones":[-1],"JKL":[145637],"CLS":[-1],"JTR":[-1],"GR Jedi":[-1],"JMK GR":[181382],"JMK Jedi":[168596],"GAS Special":[65990],"Finn":[-1]}},{"name":"Jader","id":"446271891","values":{"Shaak Ti":[-1],"JKR":[141797],"ROLO":[-1],"CLS-Alt":[-1],"KAM Squad":[138950],"Mon Mothma":[95378],"Negotiator":[462908],"JMLS":[161508],"Padme":[-1],"GL Rey":[-1],"GAS":[-1],"Clones":[-1],"JKL":[147482],"CLS":[145521],"JTR":[-1],"GR Jedi":[148272],"JMK GR":[175938],"JMK Jedi":[-1],"GAS Special":[59480],"Finn":[-1]}},{"name":"Ewoks Goin In Dry","id":"448434423","values":{"Shaak Ti":[-1],"JKR":[144851],"ROLO":[120282],"CLS-Alt":[-1],"KAM Squad":[134613],"Mon Mothma":[85886],"Negotiator":[443841],"JMLS":[167399],"Padme":[-1],"GL Rey":[168135],"GAS":[-1],"Clones":[-1],"JKL":[136085],"CLS":[-1],"JTR":[-1],"GR Jedi":[-1],"JMK GR":[173247],"JMK Jedi":[-1],"GAS Special":[61071],"Finn":[-1]}},{"name":"David","id":"451567767","values":{"Shaak Ti":[-1],"JKR":[152566],"ROLO":[125423],"CLS-Alt":[-1],"KAM Squad":[145916],"Mon Mothma":[91781],"Negotiator":[471866],"JMLS":[169799],"Padme":[-1],"GL Rey":[-1],"GAS":[-1],"Clones":[-1],"JKL":[152386],"CLS":[-1],"JTR":[-1],"GR Jedi":[-1],"JMK GR":[176733],"JMK Jedi":[-1],"GAS Special":[61836],"Finn":[-1]}},{"name":"GravelSK","id":"496916323","values":{"Shaak Ti":[-1],"JKR":[152978],"ROLO":[126447],"CLS-Alt":[-1],"KAM Squad":[145454],"Mon Mothma":[92884],"Negotiator":[472870],"JMLS":[178721],"Padme":[-1],"GL Rey":[163265],"GAS":[-1],"Clones":[-1],"JKL":[145678],"CLS":[-1],"JTR":[-1],"GR Jedi":[-1],"JMK GR":[174433],"JMK Jedi":[-1],"GAS Special":[69073],"Finn":[-1]}},{"name":"Kibleh Toht","id":"512685275","values":{"Shaak Ti":[84430],"JKR":[129493],"ROLO":[-1],"CLS-Alt":[-1],"KAM Squad":[84430],"Mon Mothma":[81766],"Negotiator":[396956],"JMLS":[177457],"Padme":[145836],"GL Rey":[-1],"GAS":[103287],"Clones":[-1],"JKL":[121731],"CLS":[145151],"JTR":[-1],"GR Jedi":[-1],"JMK GR":[-1],"JMK Jedi":[-1],"GAS Special":[61654],"Finn":[-1]}},{"name":"Shamgar","id":"514487916","values":{"Shaak Ti":[135064],"JKR":[148402],"ROLO":[102204],"CLS-Alt":[-1],"KAM Squad":[135064],"Mon Mothma":[-1],"Negotiator":[434414],"JMLS":[168016],"Padme":[125952],"GL Rey":[-1],"GAS":[-1],"Clones":[-1],"JKL":[150309],"CLS":[153877],"JTR":[-1],"GR Jedi":[-1],"JMK GR":[-1],"JMK Jedi":[-1],"GAS Special":[63508],"Finn":[-1]}},{"name":"RP","id":"524758942","values":{"Shaak Ti":[-1],"JKR":[142933],"ROLO":[-1],"CLS-Alt":[-1],"KAM Squad":[143479],"Mon Mothma":[99236],"Negotiator":[462215],"JMLS":[167451],"Padme":[-1],"GL Rey":[-1],"GAS":[-1],"Clones":[-1],"JKL":[143574],"CLS":[150665],"JTR":[-1],"GR Jedi":[-1],"JMK GR":[175312],"JMK Jedi":[-1],"GAS Special":[61866],"Finn":[98170]}},{"name":"Zem Malda","id":"527394568","values":{"Shaak Ti":[-1],"JKR":[143150],"ROLO":[-1],"CLS-Alt":[-1],"KAM Squad":[143339],"Mon Mothma":[-1],"Negotiator":[412708],"JMLS":[160611],"Padme":[-1],"GL Rey":[-1],"GAS":[-1],"Clones":[-1],"JKL":[147094],"CLS":[144907],"JTR":[-1],"GR Jedi":[-1],"JMK GR":[177865],"JMK Jedi":[-1],"GAS Special":[62101],"Finn":[-1]}},{"name":"Rendash Arend","id":"557291511","values":{"Shaak Ti":[137717],"JKR":[126549],"ROLO":[-1],"CLS-Alt":[-1],"KAM Squad":[137717],"Mon Mothma":[-1],"Negotiator":[458948],"JMLS":[-1],"Padme":[115863],"GL Rey":[-1],"GAS":[-1],"Clones":[-1],"JKL":[152333],"CLS":[130119],"JTR":[-1],"GR Jedi":[-1],"JMK GR":[-1],"JMK Jedi":[-1],"GAS Special":[63031],"Finn":[-1]}},{"name":"Mordhelm","id":"562791448","values":{"Shaak Ti":[139379],"JKR":[126790],"ROLO":[112717],"CLS-Alt":[-1],"KAM Squad":[139379],"Mon Mothma":[-1],"Negotiator":[440055],"JMLS":[-1],"Padme":[145066],"GL Rey":[-1],"GAS":[-1],"Clones":[-1],"JKL":[144079],"CLS":[-1],"JTR":[-1],"GR Jedi":[-1],"JMK GR":[-1],"JMK Jedi":[-1],"GAS Special":[63504],"Finn":[-1]}},{"name":"Frednerk","id":"655585354","values":{"Shaak Ti":[-1],"JKR":[160076],"ROLO":[95289],"CLS-Alt":[-1],"KAM Squad":[145736],"Mon Mothma":[-1],"Negotiator":[460095],"JMLS":[-1],"Padme":[-1],"GL Rey":[-1],"GAS":[-1],"Clones":[-1],"JKL":[159867],"CLS":[144019],"JTR":[-1],"GR Jedi":[-1],"JMK GR":[169884],"JMK Jedi":[-1],"GAS Special":[63278],"Finn":[-1]}},{"name":"ATX ONE","id":"659226473","values":{"Shaak Ti":[-1],"JKR":[168984],"ROLO":[132716],"CLS-Alt":[-1],"KAM Squad":[154635],"Mon Mothma":[110528],"Negotiator":[499454],"JMLS":[193770],"Padme":[-1],"GL Rey":[169874],"GAS":[-1],"Clones":[-1],"JKL":[156044],"CLS":[-1],"JTR":[159914],"GR Jedi":[-1],"JMK GR":[193002],"JMK Jedi":[-1],"GAS Special":[72164],"Finn":[-1]}},{"name":"Acesoka","id":"668136538","values":{"Shaak Ti":[-1],"JKR":[148499],"ROLO":[102408],"CLS-Alt":[-1],"KAM Squad":[147415],"Mon Mothma":[-1],"Negotiator":[465183],"JMLS":[-1],"Padme":[-1],"GL Rey":[-1],"GAS":[-1],"Clones":[-1],"JKL":[162296],"CLS":[132437],"JTR":[-1],"GR Jedi":[-1],"JMK GR":[173784],"JMK Jedi":[-1],"GAS Special":[67314],"Finn":[-1]}},{"name":"DarthScrimm","id":"695948683","values":{"Shaak Ti":[138776],"JKR":[122034],"ROLO":[118644],"CLS-Alt":[-1],"KAM Squad":[138776],"Mon Mothma":[84180],"Negotiator":[415823],"JMLS":[-1],"Padme":[132933],"GL Rey":[-1],"GAS":[-1],"Clones":[-1],"JKL":[127929],"CLS":[-1],"JTR":[-1],"GR Jedi":[-1],"JMK GR":[-1],"JMK Jedi":[-1],"GAS Special":[-1],"Finn":[71748]}},{"name":"knaggs1120","id":"722718646","values":{"Shaak Ti":[134122],"JKR":[111301],"ROLO":[71654],"CLS-Alt":[-1],"KAM Squad":[134122],"Mon Mothma":[-1],"Negotiator":[393672],"JMLS":[-1],"Padme":[124476],"GL Rey":[-1],"GAS":[-1],"Clones":[-1],"JKL":[-1],"CLS":[114972],"JTR":[-1],"GR Jedi":[-1],"JMK GR":[-1],"JMK Jedi":[-1],"GAS Special":[-1],"Finn":[-1]}},{"name":"Pﾑdme's Chﾑstity Belt","id":"725514455","values":{"Shaak Ti":[-1],"JKR":[140939],"ROLO":[-1],"CLS-Alt":[-1],"KAM Squad":[151723],"Mon Mothma":[91829],"Negotiator":[472716],"JMLS":[169493],"Padme":[-1],"GL Rey":[-1],"GAS":[-1],"Clones":[-1],"JKL":[143408],"CLS":[145484],"JTR":[-1],"GR Jedi":[-1],"JMK GR":[187719],"JMK Jedi":[-1],"GAS Special":[69920],"Finn":[131851]}},{"name":"oogway","id":"736683126","values":{"Shaak Ti":[-1],"JKR":[157321],"ROLO":[122283],"CLS-Alt":[-1],"KAM Squad":[152255],"Mon Mothma":[100945],"Negotiator":[471776],"JMLS":[174601],"Padme":[-1],"GL Rey":[163364],"GAS":[-1],"Clones":[-1],"JKL":[145547],"CLS":[-1],"JTR":[159002],"GR Jedi":[-1],"JMK GR":[187483],"JMK Jedi":[-1],"GAS Special":[65652],"Finn":[-1]}},{"name":"Anton360247","id":"757167173","values":{"Shaak Ti":[150037],"JKR":[115689],"ROLO":[125848],"CLS-Alt":[147870],"KAM Squad":[150037],"Mon Mothma":[83189],"Negotiator":[481853],"JMLS":[-1],"Padme":[153649],"GL Rey":[-1],"GAS":[-1],"Clones":[-1],"JKL":[-1],"CLS":[-1],"JTR":[-1],"GR Jedi":[-1],"JMK GR":[-1],"JMK Jedi":[-1],"GAS Special":[-1],"Finn":[72295]}},{"name":"Da Conquering One","id":"765966569","values":{"Shaak Ti":[152209],"JKR":[129819],"ROLO":[-1],"CLS-Alt":[-1],"KAM Squad":[152209],"Mon Mothma":[-1],"Negotiator":[398064],"JMLS":[-1],"Padme":[129572],"GL Rey":[-1],"GAS":[-1],"Clones":[-1],"JKL":[140887],"CLS":[138566],"JTR":[-1],"GR Jedi":[-1],"JMK GR":[-1],"JMK Jedi":[-1],"GAS Special":[-1],"Finn":[-1]}},{"name":"Al Greaf","id":"778479137","values":{"Shaak Ti":[136233],"JKR":[122225],"ROLO":[95467],"CLS-Alt":[-1],"KAM Squad":[136233],"Mon Mothma":[-1],"Negotiator":[400253],"JMLS":[-1],"Padme":[130349],"GL Rey":[-1],"GAS":[-1],"Clones":[-1],"JKL":[141707],"CLS":[149496],"JTR":[-1],"GR Jedi":[-1],"JMK GR":[-1],"JMK Jedi":[-1],"GAS Special":[28381],"Finn":[148959]}},{"name":"DAGGOBILI","id":"786851589","values":{"Shaak Ti":[-1],"JKR":[137754],"ROLO":[56206],"CLS-Alt":[-1],"KAM Squad":[141424],"Mon Mothma":[-1],"Negotiator":[449010],"JMLS":[-1],"Padme":[-1],"GL Rey":[-1],"GAS":[-1],"Clones":[-1],"JKL":[-1],"CLS":[120122],"JTR":[-1],"GR Jedi":[-1],"JMK GR":[173941],"JMK Jedi":[-1],"GAS Special":[61532],"Finn":[-1]}},{"name":"Rui Vuusen","id":"829415495","values":{"Shaak Ti":[-1],"JKR":[142832],"ROLO":[-1],"CLS-Alt":[-1],"KAM Squad":[133482],"Mon Mothma":[79142],"Negotiator":[460170],"JMLS":[-1],"Padme":[-1],"GL Rey":[-1],"GAS":[138781],"Clones":[124273],"JKL":[154464],"CLS":[129927],"JTR":[-1],"GR Jedi":[-1],"JMK GR":[179733],"JMK Jedi":[-1],"GAS Special":[65387],"Finn":[70720]}},{"name":"Flyt","id":"831894956","values":{"Shaak Ti":[-1],"JKR":[147899],"ROLO":[116831],"CLS-Alt":[-1],"KAM Squad":[142303],"Mon Mothma":[85254],"Negotiator":[466308],"JMLS":[168245],"Padme":[-1],"GL Rey":[-1],"GAS":[-1],"Clones":[-1],"JKL":[139980],"CLS":[-1],"JTR":[110368],"GR Jedi":[-1],"JMK GR":[177757],"JMK Jedi":[-1],"GAS Special":[63202],"Finn":[-1]}},{"name":"Schmuckk007","id":"858274497","values":{"Shaak Ti":[133776],"JKR":[139369],"ROLO":[127680],"CLS-Alt":[143725],"KAM Squad":[133776],"Mon Mothma":[77477],"Negotiator":[413591],"JMLS":[-1],"Padme":[132185],"GL Rey":[-1],"GAS":[-1],"Clones":[-1],"JKL":[147513],"CLS":[-1],"JTR":[-1],"GR Jedi":[-1],"JMK GR":[-1],"JMK Jedi":[-1],"GAS Special":[62677],"Finn":[72816]}},{"name":"FlibbidyDoo","id":"872314944","values":{"Shaak Ti":[106856],"JKR":[123519],"ROLO":[104722],"CLS-Alt":[-1],"KAM Squad":[106856],"Mon Mothma":[-1],"Negotiator":[-1],"JMLS":[152913],"Padme":[128692],"GL Rey":[-1],"GAS":[-1],"Clones":[-1],"JKL":[165974],"CLS":[146424],"JTR":[-1],"GR Jedi":[-1],"JMK GR":[-1],"JMK Jedi":[-1],"GAS Special":[54550],"Finn":[-1]}},{"name":"ItsTurtleTime","id":"876758471","values":{"Shaak Ti":[-1],"JKR":[149408],"CLS-Alt":[-1],"ROLO":[-1],"KAM Squad":[150924],"Mon Mothma":[-1],"Negotiator":[473475],"JMLS":[169064],"Padme":[-1],"GL Rey":[-1],"GAS":[-1],"Clones":[-1],"JKL":[147414],"CLS":[145568],"JTR":[-1],"GR Jedi":[-1],"JMK GR":[179756],"JMK Jedi":[-1],"GAS Special":[63450],"Finn":[-1]}},{"name":"Boyk Jhaatim","id":"919177443","values":{"Shaak Ti":[-1],"JKR":[148536],"CLS-Alt":[-1],"ROLO":[128459],"KAM Squad":[138639],"Mon Mothma":[84781],"Negotiator":[437884],"JMLS":[168839],"Padme":[-1],"GL Rey":[-1],"GAS":[-1],"Clones":[-1],"JKL":[151133],"CLS":[-1],"JTR":[-1],"GR Jedi":[-1],"JMK GR":[172751],"JMK Jedi":[-1],"GAS Special":[61569],"Finn":[90428]}},{"name":"ClintonKilledEpstein","id":"923593274","values":{"Shaak Ti":[-1],"JKR":[140601],"CLS-Alt":[-1],"ROLO":[125504],"KAM Squad":[150921],"Mon Mothma":[80259],"Negotiator":[462412],"JMLS":[161898],"Padme":[-1],"GL Rey":[-1],"GAS":[-1],"Clones":[-1],"JKL":[148995],"CLS":[-1],"JTR":[-1],"GR Jedi":[150272],"JMK GR":[174574],"JMK Jedi":[-1],"GAS Special":[61069],"Finn":[78614]}},{"name":"DarthKailon","id":"933888673","values":{"Shaak Ti":[-1],"JKR":[159507],"CLS-Alt":[-1],"ROLO":[122665],"KAM Squad":[151178],"Mon Mothma":[92256],"Negotiator":[477824],"JMLS":[176941],"Padme":[-1],"GL Rey":[164012],"GAS":[-1],"Clones":[-1],"JKL":[144608],"CLS":[-1],"JTR":[159402],"GR Jedi":[-1],"JMK GR":[187581],"JMK Jedi":[171862],"GAS Special":[69442],"Finn":[-1]}},{"name":"Ke Ke Mar","id":"943347694","values":{"Shaak Ti":[134269],"JKR":[140787],"CLS-Alt":[-1],"ROLO":[125278],"KAM Squad":[134269],"Mon Mothma":[88505],"Negotiator":[444676],"JMLS":[160848],"Padme":[142930],"GL Rey":[-1],"GAS":[-1],"Clones":[-1],"JKL":[121202],"CLS":[-1],"JTR":[138969],"GR Jedi":[-1],"JMK GR":[-1],"JMK Jedi":[-1],"GAS Special":[59961],"Finn":[101815]}},{"name":"HR dpt Chatty's division","id":"959622351","values":{"Shaak Ti":[-1],"JKR":[165342],"CLS-Alt":[-1],"ROLO":[-1],"KAM Squad":[145218],"Mon Mothma":[91852],"Negotiator":[472603],"JMLS":[185312],"Padme":[-1],"GL Rey":[-1],"GAS":[-1],"Clones":[-1],"JKL":[144367],"CLS":[145341],"JTR":[-1],"GR Jedi":[-1],"JMK GR":[182168],"JMK Jedi":[-1],"GAS Special":[65664],"Finn":[133471]}},{"name":"9th DOGG of SWAG","id":"987179658","values":{"Shaak Ti":[141457],"JKR":[142796],"CLS-Alt":[-1],"ROLO":[-1],"KAM Squad":[141457],"Mon Mothma":[89717],"Negotiator":[419527],"JMLS":[178227],"Padme":[149461],"GL Rey":[-1],"GAS":[-1],"Clones":[-1],"JKL":[137874],"CLS":[144065],"JTR":[-1],"GR Jedi":[-1],"JMK GR":[-1],"JMK Jedi":[-1],"GAS Special":[63748],"Finn":[90266]}},{"name":"Curren","id":"995319291","values":{"Shaak Ti":[-1],"JKR":[142612],"CLS-Alt":[-1],"ROLO":[95556],"KAM Squad":[138909],"Mon Mothma":[-1],"Negotiator":[462596],"JMLS":[-1],"Padme":[-1],"GL Rey":[-1],"GAS":[144627],"Clones":[129990],"JKL":[143929],"CLS":[127004],"JTR":[-1],"GR Jedi":[-1],"JMK GR":[173458],"JMK Jedi":[-1],"GAS Special":[63693],"Finn":[65414]}}]}