{"y":"count","dates":["04\/26\/2023"],"series":[{"name":"ClîtCommander12345","id":"124661194","values":{"Squads":[21],"G10+":[139],"Def":[10],"G12+":[110],"G13+":[77],"7*":[226],"Zetas":[171],"Off":[10]}},{"name":"Dannimadd","id":"183382135","values":{"Squads":[22],"G10+":[143],"Def":[11],"G12+":[122],"G13+":[98],"7*":[255],"Zetas":[136],"Off":[10]}},{"name":"Delmon Ciiid'r","id":"196981493","values":{"Squads":[12],"G10+":[81],"Def":[7],"G12+":[47],"G13+":[28],"7*":[210],"Zetas":[73],"Off":[5]}},{"name":"Will Obi1","id":"215141515","values":{"Squads":[18],"G10+":[127],"Def":[8],"G12+":[101],"7*":[223],"G13+":[78],"Zetas":[185],"Off":[6]}},{"name":"Droguito","id":"222224934","values":{"Squads":[18],"G10+":[101],"Def":[9],"G12+":[72],"G13+":[43],"7*":[235],"Zetas":[87],"Off":[11]}},{"name":"Berzerk Hobo","id":"252285491","values":{"Squads":[23],"G10+":[190],"Def":[12],"G12+":[149],"G13+":[85],"7*":[253],"Zetas":[188],"Off":[12]}},{"name":"Blak3oakfield","id":"277384321","values":{"Squads":[11],"G10+":[88],"Def":[7],"G12+":[74],"G13+":[53],"7*":[173],"Zetas":[106],"Off":[5]}},{"name":"JasonTheAsian","id":"316261256","values":{"Squads":[24],"G10+":[172],"Def":[11],"G12+":[140],"7*":[242],"G13+":[81],"Zetas":[182],"Off":[13]}},{"name":"NuMex","id":"331898292","values":{"Squads":[25],"G10+":[185],"Def":[13],"G12+":[170],"G13+":[64],"7*":[260],"Zetas":[178],"Off":[11]}},{"name":"ObiJuan Keithnobi","id":"355745111","values":{"Squads":[19],"G10+":[137],"Def":[11],"G12+":[112],"7*":[220],"G13+":[73],"Zetas":[150],"Off":[10]}},{"name":"Gero Zurn","id":"397437123","values":{"Squads":[22],"G10+":[169],"Def":[9],"G12+":[142],"7*":[225],"G13+":[109],"Zetas":[169],"Off":[11]}},{"name":"Soko","id":"418929655","values":{"Squads":[16],"G10+":[108],"Def":[13],"G12+":[67],"G13+":[38],"7*":[204],"Zetas":[69],"Off":[8]}},{"name":"polarariel","id":"423666999","values":{"Squads":[26],"G10+":[164],"Def":[9],"G12+":[141],"7*":[264],"G13+":[118],"Zetas":[203],"Off":[12]}},{"name":"Bsville","id":"424867781","values":{"Squads":[21],"G10+":[143],"Def":[11],"G12+":[118],"G13+":[81],"7*":[245],"Zetas":[150],"Off":[12]}},{"name":"TheFoggy","id":"433616769","values":{"Squads":[26],"G10+":[165],"Def":[8],"G12+":[145],"7*":[268],"G13+":[115],"Zetas":[210],"Off":[12]}},{"name":"Wilk79","id":"438582744","values":{"Squads":[10],"G10+":[81],"Def":[7],"G12+":[48],"G13+":[32],"7*":[149],"Zetas":[82],"Off":[6]}},{"name":"Thiffy Gorebreg","id":"442479953","values":{"Squads":[26],"G10+":[191],"Def":[11],"G12+":[160],"7*":[275],"G13+":[124],"Zetas":[212],"Off":[11]}},{"name":"Salacious Thumb","id":"444544452","values":{"Squads":[18],"G10+":[125],"Def":[10],"G12+":[95],"7*":[220],"G13+":[71],"Zetas":[132],"Off":[9]}},{"name":"YungPepr","id":"452134382","values":{"Squads":[6],"G10+":[60],"Def":[6],"G12+":[46],"G13+":[26],"7*":[93],"Zetas":[50],"Off":[3]}},{"name":"Ronzool","id":"498413548","values":{"Squads":[18],"G10+":[125],"Def":[12],"G12+":[98],"G13+":[53],"7*":[232],"Zetas":[159],"Off":[9]}},{"name":"DarthSacaMando","id":"522114916","values":{"Squads":[17],"G10+":[121],"Def":[8],"G12+":[95],"7*":[205],"G13+":[65],"Zetas":[121],"Off":[10]}},{"name":"TheWildKarrde","id":"522914351","values":{"Squads":[19],"G10+":[134],"Def":[11],"G12+":[103],"7*":[222],"G13+":[74],"Zetas":[172],"Off":[8]}},{"name":"Sixx Shooter","id":"536357128","values":{"Squads":[13],"G10+":[97],"Def":[9],"G12+":[79],"7*":[213],"G13+":[56],"Zetas":[100],"Off":[8]}},{"name":"Micahtron","id":"538511948","values":{"Squads":[21],"G10+":[150],"Def":[9],"G12+":[121],"7*":[238],"G13+":[93],"Zetas":[172],"Off":[10]}},{"name":"Rikka light side","id":"549878449","values":{"Squads":[28],"G10+":[215],"Def":[8],"G12+":[194],"7*":[284],"G13+":[126],"Zetas":[222],"Off":[13]}},{"name":"ShadyT","id":"558572552","values":{"Squads":[16],"G10+":[119],"Def":[8],"G12+":[104],"7*":[234],"G13+":[87],"Zetas":[154],"Off":[6]}},{"name":"Kilum Natta","id":"569741419","values":{"Squads":[9],"G10+":[67],"Def":[7],"G12+":[52],"7*":[133],"G13+":[40],"Zetas":[67],"Off":[5]}},{"name":"Jason","id":"576549933","values":{"Squads":[21],"G10+":[155],"Def":[8],"G12+":[125],"7*":[254],"G13+":[98],"Zetas":[193],"Off":[8]}},{"name":"Balakay","id":"621546373","values":{"Squads":[27],"G10+":[189],"Def":[10],"G12+":[174],"7*":[270],"G13+":[135],"Zetas":[199],"Off":[12]}},{"name":"Nearly Headless Nick","id":"666842776","values":{"Squads":[17],"G10+":[118],"Def":[8],"G12+":[87],"7*":[196],"G13+":[66],"Zetas":[140],"Off":[8]}},{"name":"Tim","id":"682839262","values":{"Squads":[14],"G10+":[107],"Def":[5],"G12+":[93],"7*":[177],"G13+":[80],"Zetas":[101],"Off":[6]}},{"name":"HarryTheHutt","id":"683648442","values":{"Squads":[12],"G10+":[74],"Def":[9],"G12+":[57],"7*":[187],"G13+":[30],"Zetas":[75],"Off":[5]}},{"name":"Sleazy E","id":"695822276","values":{"Squads":[21],"G10+":[147],"Def":[9],"G12+":[131],"7*":[248],"G13+":[102],"Zetas":[172],"Off":[10]}},{"name":"WWG1WG2PRISON","id":"713375299","values":{"Squads":[20],"G10+":[152],"Def":[13],"G12+":[113],"G13+":[81],"7*":[229],"Zetas":[162],"Off":[12]}},{"name":"Jason","id":"721779418","values":{"Squads":[18],"G10+":[138],"Def":[10],"G12+":[112],"7*":[232],"G13+":[105],"Zetas":[154],"Off":[8]}},{"name":"Tenzin","id":"736547728","values":{"Squads":[18],"G10+":[145],"Def":[10],"G12+":[117],"G13+":[101],"7*":[260],"Zetas":[185],"Off":[7]}},{"name":"Zoltar","id":"739779589","values":{"Squads":[20],"G10+":[136],"Def":[7],"G12+":[115],"7*":[194],"G13+":[89],"Zetas":[150],"Off":[8]}},{"name":"MrDusty","id":"754891619","values":{"Squads":[20],"G10+":[104],"Def":[12],"G12+":[70],"7*":[231],"G13+":[41],"Zetas":[102],"Off":[12]}},{"name":"name","id":"779262258","values":{"Squads":[15],"G10+":[105],"Def":[5],"G12+":[90],"G13+":[62],"7*":[196],"Zetas":[141],"Off":[5]}},{"name":"DarthMaul5","id":"783529757","values":{"Squads":[14],"G10+":[94],"Def":[10],"G12+":[51],"7*":[173],"G13+":[36],"Zetas":[75],"Off":[9]}},{"name":"The Great One F2P","id":"816728211","values":{"Squads":[10],"G10+":[75],"Def":[6],"G12+":[49],"7*":[188],"G13+":[25],"Zetas":[60],"Off":[5]}},{"name":"Scrotie McBoogerballs","id":"832986271","values":{"Squads":[14],"G10+":[105],"Def":[7],"G12+":[92],"G13+":[41],"7*":[197],"Zetas":[121],"Off":[9]}},{"name":"Adonis13","id":"852276575","values":{"Squads":[23],"G10+":[170],"Def":[10],"G12+":[149],"G13+":[113],"7*":[239],"Zetas":[201],"Off":[10]}},{"name":"Stephman Darksipper","id":"864462482","values":{"Squads":[27],"G10+":[162],"Def":[14],"G12+":[145],"7*":[266],"G13+":[77],"Zetas":[169],"Off":[12]}},{"name":"Scarb Fir","id":"872612614","values":{"Squads":[19],"G10+":[120],"Def":[8],"G12+":[88],"7*":[198],"G13+":[71],"Zetas":[133],"Off":[8]}},{"name":"Jivan Mukti","id":"928423758","values":{"Squads":[24],"G10+":[130],"Def":[12],"G12+":[105],"7*":[254],"G13+":[58],"Zetas":[133],"Off":[11]}},{"name":"Krumpch","id":"961147939","values":{"Squads":[12],"G10+":[72],"Def":[7],"G12+":[56],"7*":[166],"G13+":[47],"Zetas":[85],"Off":[5]}},{"name":"Plagarian","id":"974618589","values":{"Squads":[22],"G10+":[137],"Def":[10],"G12+":[108],"7*":[248],"G13+":[73],"Zetas":[201],"Off":[12]}},{"name":"lottatrotta69","id":"974943562","values":{"Squads":[19],"G10+":[140],"Def":[9],"G12+":[103],"7*":[262],"G13+":[78],"Zetas":[153],"Off":[8]}},{"name":"Meetra Surik","id":"989184811","values":{"Squads":[22],"G10+":[143],"Def":[12],"G12+":[121],"7*":[261],"G13+":[90],"Zetas":[144],"Off":[10]}}]}